CAF/__init__.py
CAF/version.py
CAF/features/binary.py
CAF/features/binary_extended.py
CAF/features/binary_helper.py
CAF/features/encoding.py
CAF/features/generator.py
CAF/features/quaternary.py
CAF/features/quaternary_helper.py
CAF/features/ternary.py
CAF/features/ternary_extended.py
CAF/features/ternary_helper.py
CAF/features/transform.py
CAF/features/universal.py
CAF/features/universal_extended.py
CAF/features/universal_helper.py
composition_analyzer_featurizer-0.0.2.dist-info/licenses/AUTHORS.rst
composition_analyzer_featurizer-0.0.2.dist-info/licenses/LICENSE.rst
composition_analyzer_featurizer-0.0.2.dist-info/METADATA
composition_analyzer_featurizer-0.0.2.dist-info/WHEEL
composition_analyzer_featurizer-0.0.2.dist-info/top_level.txt
composition_analyzer_featurizer-0.0.2.dist-info/RECORD
